{
    "normal": {
        "63000": 1,
        "350000": 1,
        "475000": 1,
        "1025000": 2,
        "1563000": 2.5,
        "3375000": 3,
        "4250000": 3.5
    },
    "hard": {
        "78000": 1,
        "438000": 1,
        "594000": 1,
        "1281000": 2,
        "1953000": 2.5,
        "4219000": 3,
        "5313000": 3.5
    },
    "legendary": {
        "100000": 1,
        "560000": 1,
        "760000": 1,
        "1640000": 2,
        "2500000": 2.5,
        "5400000": 3,
        "6800000": 3.5
    },
    "nightmare": {
        "125000": 1,
        "700000": 1,
        "950000": 1,
        "2050000": 2,
        "3125000": 2.5,
        "6750000": 3,
        "8500000": 3.5
    }
}
